flasksr
