Metadata-Version: 1.1
Name: flasksr
Version: 0.6
Summary: Start streaming HTTP Responses based on your page layout for Flask and improve Time for First Paint.
Home-page: https://github.com/arpitbbhayani/flasksr
Author: Arpit Bhayani
Author-email: arpit.bhayani@gmail.com
License: UNKNOWN
Download-URL: https://github.com/arpitbbhayani/flasksr
Keywords: flask,response,fast website,fast page load
Platform: UNKNOWN
